django_payu_payments-0.1.3.dist-info/DESCRIPTION.rst
django_payu_payments-0.1.3.dist-info/METADATA
django_payu_payments-0.1.3.dist-info/RECORD
django_payu_payments-0.1.3.dist-info/SOURCES.txt.py
django_payu_payments-0.1.3.dist-info/WHEEL
django_payu_payments-0.1.3.dist-info/dependency_links.txt.py
django_payu_payments-0.1.3.dist-info/metadata.json
django_payu_payments-0.1.3.dist-info/requires.txt.py
django_payu_payments-0.1.3.dist-info/top_level.txt
django_payu_payments-0.1.3.dist-info/top_level.txt.py
payu/__init__.py
payu/admin.py
payu/api.py
payu/apps.py
payu/models.py
payu/settings.py
payu/setup.py
payu/urls.py
payu/urls_api.py
payu/locale/pl/LC_MESSAGES/django.mo
payu/locale/pl/LC_MESSAGES/django.po
payu/migrations/0001_initial.py
payu/migrations/0002_auto_20160313_2006.py
payu/migrations/0003_auto_20160601_0007.py
payu/migrations/__init__.py
