Metadata-Version: 2.0
Name: django-payu-payments
Version: 0.1.3
Summary: PayU integration for Django.
Home-page: https://github.com/michalwerner/django-payu-payments
Author: Michal Werner
Author-email: michal@hurtowniapixeli.pl
License: MIT
Platform: UNKNOWN
Classifier: Development Status :: 3 - Alpha
Classifier: Intended Audience :: Developers
Classifier: Environment :: Web Environment
Classifier: Framework :: Django
Classifier: License :: OSI Approved :: MIT License
Classifier: Operating System :: OS Independent
Classifier: Programming Language :: Python :: 3
Requires-Dist: django
Requires-Dist: django-ipware
Requires-Dist: jsonfield
Requires-Dist: requests
